hanjadict/__about__.py
hanjadict/__init__.py
hanjadict/dev.py
hanjadict/main.py
hanjadict/table.json
hanjadict/table.py
hanjadict-0.4.0.dist-info/METADATA
hanjadict-0.4.0.dist-info/WHEEL
hanjadict-0.4.0.dist-info/licenses/LICENSE
hanjadict-0.4.0.dist-info/RECORD
