Metadata-Version: 2.4
Name: hanjadict
Version: 0.4.0
Summary: A lightweight Python library for looking up Korean Hanja characters with their 훈음 (Hun-eum) meanings and pronunciations
Project-URL: Homepage, https://github.com/seyoungsong/hanjadict
Project-URL: Issues, https://github.com/seyoungsong/hanjadict/issues
Author-email: Seyoung Song <seyoung.song@kaist.ac.kr>
License-Expression: MIT
License-File: LICENSE
Classifier: Operating System :: OS Independent
Classifier: Programming Language :: Python :: 3
Requires-Python: >=3.8
Provides-Extra: dev
Requires-Dist: build; extra == 'dev'
Requires-Dist: isort; extra == 'dev'
Requires-Dist: mypy; extra == 'dev'
Requires-Dist: pytest; extra == 'dev'
Requires-Dist: ruff; extra == 'dev'
Requires-Dist: twine; extra == 'dev'
